dsk/data.py
dsk/plots.py
dsk-0.1.0.dist-info/LICENSE
dsk-0.1.0.dist-info/WHEEL
dsk-0.1.0.dist-info/METADATA
dsk-0.1.0.dist-info/RECORD
